tkup/__init__.py
tkup/_widgets.py
tkup/any_tk.py
tkup/gui.py
tkup-1.2.0.dist-info/DESCRIPTION.rst
tkup-1.2.0.dist-info/METADATA
tkup-1.2.0.dist-info/RECORD
tkup-1.2.0.dist-info/WHEEL
tkup-1.2.0.dist-info/metadata.json
tkup-1.2.0.dist-info/top_level.txt
