Metadata-Version: 2.0
Name: tkup
Version: 1.2.0
Summary: Hierarchical Tkinter wrapper
Home-page: https://github.com/mtkennerly/tkup
Author: Matthew T. Kennerly (mtkennerly)
Author-email: mtkennerly@gmail.com
License: MIT
Keywords: gui tkinter wrapper
Platform: UNKNOWN
Classifier: Development Status :: 5 - Production/Stable
Classifier: Intended Audience :: End Users/Desktop
Classifier: License :: OSI Approved :: MIT License
Classifier: Natural Language :: English
Classifier: Programming Language :: Python
Classifier: Programming Language :: Python :: 3
Classifier: Topic :: Software Development :: User Interfaces
